ODWC/__init__.py
ODWC/main.py
ODWC-1.0rc4.dist-info/LICENSE
ODWC-1.0rc4.dist-info/METADATA
ODWC-1.0rc4.dist-info/WHEEL
ODWC-1.0rc4.dist-info/top_level.txt
ODWC-1.0rc4.dist-info/RECORD
