Metadata-Version: 2.1
Name: ODWC
Version: 1.0rc4
Summary: Open Driver Waypoint Coordinator
Home-page: https://github.com/Ewpratten/ODWC
Author: Evan Pratten
Author-email: ewpratten@gmail.com
License: GPLv3
Platform: UNKNOWN
Classifier: Programming Language :: Python :: 3
Classifier: Operating System :: OS Independent
Classifier: Development Status :: 5 - Production/Stable
Requires-Dist: requests
Requires-Dist: scipy
